xxyy/__init__.py
xxyy/requests/__init__.py
xxyy/requests/adapters.py
xxyy/requests/auth.py
xxyy-0.1.5.dist-info/WHEEL
xxyy-0.1.5.dist-info/METADATA
xxyy-0.1.5.dist-info/RECORD
